main.py
zettle-0.0.1.dist-info/METADATA
zettle-0.0.1.dist-info/WHEEL
zettle-0.0.1.dist-info/top_level.txt
zettle-0.0.1.dist-info/RECORD
