Metadata-Version: 2.1
Name: zettle
Version: 0.0.1
Summary: Python API wrapper for Zettle (zettle.com)
Classifier: Programming Language :: Python :: 3
Classifier: License :: OSI Approved :: MIT License
Classifier: Operating System :: OS Independent
Requires-Python: >=3.7
